{
  "is_book": false,
  "anchor": "master-toc",
  "file": "index.html",
  "name": "Documentation Contents",
  "headings": [
    {
      "level": 1,
      "anchor": "Important-Manuals",
      "text": "1 Important Manuals"
    },
    {
      "level": 2,
      "anchor": "Release-Notes",
      "text": "Release Notes"
    },
    {
      "level": 2,
      "anchor": "Installation-Guide",
      "text": "Installation Guide"
    },
    {
      "level": 2,
      "anchor": "Getting-Started",
      "text": "Getting Started"
    },
    {
      "level": 2,
      "anchor": "Simics-Users-Guide",
      "text": "Simics User's Guide"
    },
    {
      "level": 2,
      "anchor": "Analyzer-Users-Guide",
      "text": "Analyzer User's Guide"
    },
    {
      "level": 2,
      "anchor": "Ethernet-Networking-Technology-Guide",
      "text": "Ethernet Networking Technology Guide"
    },
    {
      "level": 2,
      "anchor": "Product-Family-Overview",
      "text": "Product Family Overview"
    },
    {
      "level": 2,
      "anchor": "Simics-Target-Guides",
      "text": "Simics Target Guides"
    },
    {
      "level": 2,
      "anchor": "Simics-Reference-Manuals",
      "text": "Simics Reference Manuals"
    },
    {
      "level": 2,
      "anchor": "Model-Builder-Users-Guide",
      "text": "Model Builder User's Guide"
    },
    {
      "level": 2,
      "anchor": "DML-Reference-Manual",
      "text": "DML Reference Manual"
    },
    {
      "level": 2,
      "anchor": "Additional-Manuals",
      "text": "Additional Manuals"
    },
    {
      "level": 1,
      "anchor": "Conventions",
      "text": "2 Conventions"
    }
  ],
  "children": []
}